{
  "data": {
    "article": {},
    "attachments": {},
    "author_id": "1545801302617116672",
    "conversation_id": "2063616378922565738",
    "created_at": "2026-06-07T16:35:37.000Z",
    "edit_controls": {
      "editable_until": "2026-06-07T17:35:37.000Z",
      "edits_remaining": 5,
      "is_edit_eligible": false
    },
    "edit_history_tweet_ids": [
      "2063661166073950655"
    ],
    "entities": {
      "mentions": [
        {
          "end": 15,
          "id": "2042276998668525573",
          "start": 0,
          "username": "SakurabaAya514"
        }
      ]
    },
    "geo": {},
    "id": "2063661166073950655",
    "in_reply_to_user_id": "2042276998668525573",
    "lang": "zh",
    "note_tweet": {
      "entities": {}
    },
    "possibly_sensitive": false,
    "public_metrics": {
      "bookmark_count": 0,
      "impression_count": 0,
      "like_count": 0,
      "quote_count": 0,
      "reply_count": 0,
      "retweet_count": 0
    },
    "referenced_tweets": [
      {
        "id": "2063616378922565738",
        "type": "replied_to"
      }
    ],
    "reply_settings": "everyone",
    "text": "@SakurabaAya514 加珍珠小料😡👊"
  },
  "includes": {
    "media": [
      {
        "height": 1440,
        "media_key": "3_2063616371662180353",
        "public_metrics": {},
        "type": "photo",
        "url": "https://pbs.twimg.com/media/HKNwKBGa0AEgSiw.jpg",
        "width": 1080
      }
    ],
    "tweets": [
      {
        "article": {},
        "attachments": {},
        "author_id": "1545801302617116672",
        "conversation_id": "2063616378922565738",
        "created_at": "2026-06-07T16:35:37.000Z",
        "edit_controls": {
          "editable_until": "2026-06-07T17:35:37.000Z",
          "edits_remaining": 5,
          "is_edit_eligible": false
        },
        "edit_history_tweet_ids": [
          "2063661166073950655"
        ],
        "entities": {
          "mentions": [
            {
              "end": 15,
              "id": "2042276998668525573",
              "start": 0,
              "username": "SakurabaAya514"
            }
          ]
        },
        "geo": {},
        "id": "2063661166073950655",
        "in_reply_to_user_id": "2042276998668525573",
        "lang": "zh",
        "note_tweet": {
          "entities": {}
        },
        "possibly_sensitive": false,
        "public_metrics": {
          "bookmark_count": 0,
          "impression_count": 0,
          "like_count": 0,
          "quote_count": 0,
          "reply_count": 0,
          "retweet_count": 0
        },
        "referenced_tweets": [
          {
            "id": "2063616378922565738",
            "type": "replied_to"
          }
        ],
        "reply_settings": "everyone",
        "text": "@SakurabaAya514 加珍珠小料😡👊"
      },
      {
        "article": {},
        "attachments": {
          "media_keys": [
            "3_2063616371662180353"
          ]
        },
        "author_id": "2042276998668525573",
        "context_annotations": [
          {
            "domain": {
              "description": "Categories within Brand Verticals that narrow down the scope of Brands",
              "id": "46",
              "name": "Business Taxonomy"
            },
            "entity": {
              "description": "Brands, companies, advertisers and every non-person handle with the profit intent and related to foods & beverages such as snacks, soft drinks, beers.",
              "id": "1557696888568045569",
              "name": "Food & Beverage Business"
            }
          }
        ],
        "conversation_id": "2063616378922565738",
        "created_at": "2026-06-07T13:37:39.000Z",
        "edit_controls": {
          "editable_until": "2026-06-07T14:37:39.000Z",
          "edits_remaining": 5,
          "is_edit_eligible": true
        },
        "edit_history_tweet_ids": [
          "2063616378922565738"
        ],
        "entities": {
          "urls": [
            {
              "display_url": "pic.x.com/dIhqzJm8x5",
              "end": 50,
              "expanded_url": "https://x.com/SakurabaAya514/status/2063616378922565738/photo/1",
              "media_key": "3_2063616371662180353",
              "start": 27,
              "url": "https://t.co/dIhqzJm8x5"
            }
          ]
        },
        "geo": {},
        "id": "2063616378922565738",
        "lang": "zh",
        "note_tweet": {
          "entities": {}
        },
        "possibly_sensitive": false,
        "public_metrics": {
          "bookmark_count": 0,
          "impression_count": 197,
          "like_count": 9,
          "quote_count": 0,
          "reply_count": 3,
          "retweet_count": 0
        },
        "reply_settings": "everyone",
        "text": "晚饭不知道吃什么了\n事已至此\n先吃个蜜雪冰城冰淇淋吧 https://t.co/dIhqzJm8x5"
      }
    ],
    "users": [
      {
        "created_at": "2022-07-09T16:05:40.000Z",
        "description": "MTF🏳️‍⚧️ 无证含糖 怀疑状态 UTC+8\n戒 OD & 自伤 中......\n是的我玩原神异环终末地卡拉彼丘啤酒烧烤😎😎😎\n求求你了求求你了进来玩⬇️",
        "entities": {
          "url": {
            "urls": [
              {
                "display_url": "minecraftxfj.top",
                "end": 23,
                "expanded_url": "https://minecraftxfj.top",
                "start": 0,
                "url": "https://t.co/zYxENR54VJ"
              }
            ]
          }
        },
        "id": "1545801302617116672",
        "location": "Inner Mongolia,P.R.China",
        "name": "夜桜侵峰～",
        "pinned_tweet_id": "2061128300869919213",
        "profile_image_url": "https://pbs.twimg.com/profile_images/1995204955968557056/XnPwmQB3_normal.jpg",
        "protected": false,
        "public_metrics": {
          "followers_count": 31,
          "following_count": 83,
          "like_count": 45,
          "listed_count": 0,
          "media_count": 53,
          "tweet_count": 531
        },
        "url": "https://t.co/zYxENR54VJ",
        "username": "Minecraftxfj",
        "verified": false
      },
      {
        "created_at": "2026-04-09T16:22:54.000Z",
        "description": "来自坎通国（现居巴蜀）/东方project/魔裁/Arcaea/舞萌/键政⚠️/双相情感障碍⚠️/亚文化B/欢迎互fo（会看成分致歉）/LGBTQ+🏳️‍🌈友好/友跨🏳️‍⚧️\n主要在X上网冲浪评论搞抽象为主，发帖主要是日常生活和碎碎念，以及负面推文⚠️",
        "id": "2042276998668525573",
        "name": "赤月",
        "pinned_tweet_id": "2063643511128522806",
        "profile_image_url": "https://pbs.twimg.com/profile_images/2062600655634907136/sl1r5PSg_normal.jpg",
        "protected": false,
        "public_metrics": {
          "followers_count": 310,
          "following_count": 462,
          "like_count": 6262,
          "listed_count": 0,
          "media_count": 169,
          "tweet_count": 1902
        },
        "username": "SakurabaAya514",
        "verified": false
      }
    ]
  }
}