{
  "data": {
    "article": {},
    "attachments": {},
    "author_id": "1545801302617116672",
    "conversation_id": "2071152136369426730",
    "created_at": "2026-06-29T04:22:07.000Z",
    "edit_controls": {
      "editable_until": "2026-06-29T05:22:07.000Z",
      "edits_remaining": 5,
      "is_edit_eligible": false
    },
    "edit_history_tweet_ids": [
      "2071449108242743596"
    ],
    "entities": {
      "mentions": [
        {
          "end": 13,
          "id": "1708489817191821312",
          "start": 0,
          "username": "1224HuangJin"
        },
        {
          "end": 22,
          "id": "3245069205",
          "start": 14,
          "username": "PGDynes"
        }
      ]
    },
    "geo": {},
    "id": "2071449108242743596",
    "in_reply_to_user_id": "1708489817191821312",
    "lang": "zh",
    "note_tweet": {
      "entities": {}
    },
    "possibly_sensitive": false,
    "public_metrics": {
      "bookmark_count": 0,
      "impression_count": 0,
      "like_count": 0,
      "quote_count": 0,
      "reply_count": 0,
      "retweet_count": 0
    },
    "referenced_tweets": [
      {
        "id": "2071367456623313393",
        "type": "replied_to"
      }
    ],
    "reply_settings": "everyone",
    "text": "@1224HuangJin @PGDynes 已严肃开启空调"
  },
  "includes": {
    "tweets": [
      {
        "article": {},
        "attachments": {},
        "author_id": "1545801302617116672",
        "conversation_id": "2071152136369426730",
        "created_at": "2026-06-29T04:22:07.000Z",
        "edit_controls": {
          "editable_until": "2026-06-29T05:22:07.000Z",
          "edits_remaining": 5,
          "is_edit_eligible": false
        },
        "edit_history_tweet_ids": [
          "2071449108242743596"
        ],
        "entities": {
          "mentions": [
            {
              "end": 13,
              "id": "1708489817191821312",
              "start": 0,
              "username": "1224HuangJin"
            },
            {
              "end": 22,
              "id": "3245069205",
              "start": 14,
              "username": "PGDynes"
            }
          ]
        },
        "geo": {},
        "id": "2071449108242743596",
        "in_reply_to_user_id": "1708489817191821312",
        "lang": "zh",
        "note_tweet": {
          "entities": {}
        },
        "possibly_sensitive": false,
        "public_metrics": {
          "bookmark_count": 0,
          "impression_count": 0,
          "like_count": 0,
          "quote_count": 0,
          "reply_count": 0,
          "retweet_count": 0
        },
        "referenced_tweets": [
          {
            "id": "2071367456623313393",
            "type": "replied_to"
          }
        ],
        "reply_settings": "everyone",
        "text": "@1224HuangJin @PGDynes 已严肃开启空调"
      },
      {
        "article": {},
        "attachments": {},
        "author_id": "1708489817191821312",
        "conversation_id": "2071152136369426730",
        "created_at": "2026-06-28T22:57:40.000Z",
        "edit_controls": {
          "editable_until": "2026-06-28T23:57:40.000Z",
          "edits_remaining": 5,
          "is_edit_eligible": false
        },
        "edit_history_tweet_ids": [
          "2071367456623313393"
        ],
        "entities": {
          "mentions": [
            {
              "end": 8,
              "id": "3245069205",
              "start": 0,
              "username": "PGDynes"
            }
          ]
        },
        "geo": {},
        "id": "2071367456623313393",
        "in_reply_to_user_id": "3245069205",
        "lang": "zh",
        "note_tweet": {
          "entities": {}
        },
        "possibly_sensitive": false,
        "public_metrics": {
          "bookmark_count": 0,
          "impression_count": 5,
          "like_count": 0,
          "quote_count": 0,
          "reply_count": 0,
          "retweet_count": 0
        },
        "referenced_tweets": [
          {
            "id": "2071152136369426730",
            "type": "replied_to"
          }
        ],
        "reply_settings": "everyone",
        "text": "@PGDynes Please STOP!\n46度你是要我死吗？"
      }
    ],
    "users": [
      {
        "created_at": "2022-07-09T16:05:40.000Z",
        "description": "MTF🏳️‍⚧️ 无证含糖 怀疑状态 高三😱\n戒 OD & 自伤 中......\n要和窝互 fo 嘛 qwq（？\n* X 有时吞 follow 和评论，如果发现超过一天了我还没有回 fo 或者评论您，可以私信我，谢谢❤️\n@xunfengjun666 转生😈👍\n友链&视奸&捐赠 and so on⬇️",
        "entities": {
          "description": {
            "mentions": [
              {
                "end": 125,
                "start": 111,
                "username": "xunfengjun666"
              }
            ]
          },
          "url": {
            "urls": [
              {
                "display_url": "minecraftxfj.top",
                "end": 23,
                "expanded_url": "https://minecraftxfj.top",
                "start": 0,
                "url": "https://t.co/zYxENR54VJ"
              }
            ]
          }
        },
        "id": "1545801302617116672",
        "location": "Inner Mongolia,P.R.China",
        "name": "夜桜侵雪～🫪",
        "pinned_tweet_id": "2061128300869919213",
        "profile_image_url": "https://pbs.twimg.com/profile_images/1995204955968557056/XnPwmQB3_normal.jpg",
        "protected": false,
        "public_metrics": {
          "followers_count": 196,
          "following_count": 281,
          "like_count": 87,
          "listed_count": 0,
          "media_count": 180,
          "tweet_count": 1527
        },
        "url": "https://t.co/zYxENR54VJ",
        "username": "Minecraftxfj",
        "verified": true
      },
      {
        "created_at": "2023-10-01T14:31:50.000Z",
        "description": "",
        "id": "1708489817191821312",
        "name": "夜影、Night Shadow",
        "pinned_tweet_id": "1845105108427616385",
        "profile_image_url": "https://pbs.twimg.com/profile_images/1834602675859501056/iPCN_1_Q_normal.jpg",
        "protected": false,
        "public_metrics": {
          "followers_count": 23,
          "following_count": 77,
          "like_count": 2933,
          "listed_count": 0,
          "media_count": 5,
          "tweet_count": 691
        },
        "url": "",
        "username": "1224HuangJin",
        "verified": false
      },
      {
        "created_at": "2015-05-10T17:26:53.000Z",
        "description": "MD - https://t.co/R4lefkSKKF | Advancing climate resilience through Sustainable Surface Radiative Thermal Management (SRTM) research https://t.co/rpCKuXuRX7",
        "entities": {
          "description": {
            "urls": [
              {
                "display_url": "MEER.org",
                "end": 28,
                "expanded_url": "http://MEER.org",
                "start": 5,
                "url": "https://t.co/R4lefkSKKF"
              },
              {
                "display_url": "substack.com/@peterdynes",
                "end": 156,
                "expanded_url": "http://substack.com/@peterdynes",
                "start": 133,
                "url": "https://t.co/rpCKuXuRX7"
              }
            ]
          },
          "url": {
            "urls": [
              {
                "display_url": "meer.org",
                "end": 23,
                "expanded_url": "http://meer.org",
                "start": 0,
                "url": "https://t.co/rc1pmYhoWN"
              }
            ]
          }
        },
        "id": "3245069205",
        "location": "Belfast ",
        "name": "Peter Dynes",
        "profile_image_url": "https://pbs.twimg.com/profile_images/1540968690568646657/yj5wBWqG_normal.jpg",
        "protected": false,
        "public_metrics": {
          "followers_count": 50879,
          "following_count": 956,
          "like_count": 10472,
          "listed_count": 575,
          "media_count": 3474,
          "tweet_count": 14913
        },
        "url": "https://t.co/rc1pmYhoWN",
        "username": "PGDynes",
        "verified": false
      }
    ]
  }
}