{
  "data": {
    "article": {},
    "attachments": {},
    "author_id": "1545801302617116672",
    "conversation_id": "2061682849833718171",
    "created_at": "2026-06-02T18:42:23.000Z",
    "edit_controls": {
      "editable_until": "2026-06-02T19:42:23.000Z",
      "edits_remaining": 5,
      "is_edit_eligible": false
    },
    "edit_history_tweet_ids": [
      "2061881126357217596"
    ],
    "entities": {
      "mentions": [
        {
          "end": 12,
          "id": "2024361959941165058",
          "start": 0,
          "username": "_itx_laila_"
        },
        {
          "end": 18,
          "id": "1720665183188922368",
          "start": 13,
          "username": "grok"
        }
      ]
    },
    "geo": {},
    "id": "2061881126357217596",
    "in_reply_to_user_id": "2024361959941165058",
    "lang": "zh",
    "note_tweet": {
      "entities": {}
    },
    "possibly_sensitive": false,
    "public_metrics": {
      "bookmark_count": 0,
      "impression_count": 0,
      "like_count": 0,
      "quote_count": 0,
      "reply_count": 0,
      "retweet_count": 0
    },
    "referenced_tweets": [
      {
        "id": "2061682849833718171",
        "type": "replied_to"
      }
    ],
    "reply_settings": "everyone",
    "text": "@_itx_laila_ @grok 恭喜你学会了并联"
  },
  "includes": {
    "media": [
      {
        "height": 912,
        "media_key": "3_2061682837250826240",
        "public_metrics": {},
        "type": "photo",
        "url": "https://pbs.twimg.com/media/HJyRngHa4AAasUn.jpg",
        "width": 1178
      }
    ],
    "tweets": [
      {
        "article": {},
        "attachments": {},
        "author_id": "1545801302617116672",
        "conversation_id": "2061682849833718171",
        "created_at": "2026-06-02T18:42:23.000Z",
        "edit_controls": {
          "editable_until": "2026-06-02T19:42:23.000Z",
          "edits_remaining": 5,
          "is_edit_eligible": false
        },
        "edit_history_tweet_ids": [
          "2061881126357217596"
        ],
        "entities": {
          "mentions": [
            {
              "end": 12,
              "id": "2024361959941165058",
              "start": 0,
              "username": "_itx_laila_"
            },
            {
              "end": 18,
              "id": "1720665183188922368",
              "start": 13,
              "username": "grok"
            }
          ]
        },
        "geo": {},
        "id": "2061881126357217596",
        "in_reply_to_user_id": "2024361959941165058",
        "lang": "zh",
        "note_tweet": {
          "entities": {}
        },
        "possibly_sensitive": false,
        "public_metrics": {
          "bookmark_count": 0,
          "impression_count": 0,
          "like_count": 0,
          "quote_count": 0,
          "reply_count": 0,
          "retweet_count": 0
        },
        "referenced_tweets": [
          {
            "id": "2061682849833718171",
            "type": "replied_to"
          }
        ],
        "reply_settings": "everyone",
        "text": "@_itx_laila_ @grok 恭喜你学会了并联"
      },
      {
        "article": {},
        "attachments": {
          "media_keys": [
            "3_2061682837250826240"
          ]
        },
        "author_id": "2024361959941165058",
        "conversation_id": "2061682849833718171",
        "created_at": "2026-06-02T05:34:30.000Z",
        "edit_controls": {
          "editable_until": "2026-06-02T06:34:30.000Z",
          "edits_remaining": 5,
          "is_edit_eligible": true
        },
        "edit_history_tweet_ids": [
          "2061682849833718171"
        ],
        "entities": {
          "mentions": [
            {
              "end": 9,
              "id": "1720665183188922368",
              "start": 4,
              "username": "grok"
            }
          ],
          "urls": [
            {
              "display_url": "pic.x.com/jpPCWDbpI8",
              "end": 90,
              "expanded_url": "https://x.com/_itx_laila_/status/2061682849833718171/photo/1",
              "media_key": "3_2061682837250826240",
              "start": 67,
              "url": "https://t.co/jpPCWDbpI8"
            }
          ]
        },
        "geo": {},
        "id": "2061682849833718171",
        "lang": "en",
        "note_tweet": {
          "entities": {}
        },
        "possibly_sensitive": false,
        "public_metrics": {
          "bookmark_count": 382,
          "impression_count": 2367174,
          "like_count": 2189,
          "quote_count": 20,
          "reply_count": 370,
          "retweet_count": 384
        },
        "reply_settings": "everyone",
        "text": "Hey @grok  What will happen if I plug this switch into the socket? https://t.co/jpPCWDbpI8"
      }
    ],
    "users": [
      {
        "created_at": "2022-07-09T16:05:40.000Z",
        "description": "MTF🏳️‍⚧️ 无证含糖 Overdose UTC+8\nbuff 叠满了\n进来玩⬇️",
        "entities": {
          "url": {
            "urls": [
              {
                "display_url": "minecraftxfj.top",
                "end": 23,
                "expanded_url": "https://minecraftxfj.top",
                "start": 0,
                "url": "https://t.co/zYxENR54VJ"
              }
            ]
          }
        },
        "id": "1545801302617116672",
        "name": "夜桜侵峰～",
        "pinned_tweet_id": "2061128300869919213",
        "profile_image_url": "https://pbs.twimg.com/profile_images/1995204955968557056/XnPwmQB3_normal.jpg",
        "protected": false,
        "public_metrics": {
          "followers_count": 27,
          "following_count": 78,
          "like_count": 47,
          "listed_count": 0,
          "media_count": 43,
          "tweet_count": 392
        },
        "url": "https://t.co/zYxENR54VJ",
        "username": "Minecraftxfj",
        "verified": false
      },
      {
        "created_at": "2026-02-19T05:54:52.000Z",
        "description": "Constantly evolving.",
        "id": "2024361959941165058",
        "name": "🌸",
        "pinned_tweet_id": "2061682849833718171",
        "profile_image_url": "https://pbs.twimg.com/profile_images/2024362665104330756/BCFxgUqk_normal.jpg",
        "protected": false,
        "public_metrics": {
          "followers_count": 1221,
          "following_count": 1222,
          "like_count": 2491,
          "listed_count": 0,
          "media_count": 11,
          "tweet_count": 2039
        },
        "username": "_itx_laila_",
        "verified": true
      },
      {
        "created_at": "2023-11-04T04:52:34.000Z",
        "description": "@grok it",
        "entities": {
          "description": {
            "mentions": [
              {
                "end": 5,
                "start": 0,
                "username": "grok"
              }
            ]
          },
          "url": {
            "urls": [
              {
                "display_url": "grok.com/download",
                "end": 23,
                "expanded_url": "http://grok.com/download",
                "start": 0,
                "url": "https://t.co/fqNKQSjjG9"
              }
            ]
          }
        },
        "id": "1720665183188922368",
        "name": "Grok",
        "profile_image_url": "https://pbs.twimg.com/profile_images/2057885623374290944/lmj0pawP_normal.jpg",
        "protected": false,
        "public_metrics": {
          "followers_count": 8781984,
          "following_count": 5,
          "like_count": 101,
          "listed_count": 6908,
          "media_count": 9002633,
          "tweet_count": 127820120
        },
        "url": "https://t.co/fqNKQSjjG9",
        "username": "grok",
        "verified": true
      }
    ]
  }
}