{
  "data": {
    "article": {},
    "attachments": {},
    "author_id": "1545801302617116672",
    "context_annotations": [
      {
        "domain": {
          "description": "Named people in the world like Nelson Mandela",
          "id": "10",
          "name": "Person"
        },
        "entity": {
          "description": "Xi Jinping",
          "id": "852769182315761664",
          "name": "Xi Jinping"
        }
      },
      {
        "domain": {
          "description": "Politicians in the world, like Joe Biden",
          "id": "35",
          "name": "Politician"
        },
        "entity": {
          "description": "Xi Jinping",
          "id": "852769182315761664",
          "name": "Xi Jinping"
        }
      },
      {
        "domain": {
          "description": "A taxonomy of user interests. ",
          "id": "131",
          "name": "Unified Twitter Taxonomy"
        },
        "entity": {
          "description": "Politics",
          "id": "847878884917886977",
          "name": "Politics"
        }
      },
      {
        "domain": {
          "description": "A taxonomy of user interests. ",
          "id": "131",
          "name": "Unified Twitter Taxonomy"
        },
        "entity": {
          "description": "Xi Jinping",
          "id": "852769182315761664",
          "name": "Xi Jinping"
        }
      },
      {
        "domain": {
          "description": "A taxonomy of user interests. ",
          "id": "131",
          "name": "Unified Twitter Taxonomy"
        },
        "entity": {
          "description": "Politician",
          "id": "1070032753834438656",
          "name": "Political figures"
        }
      }
    ],
    "conversation_id": "2066218044133962140",
    "created_at": "2026-06-14T17:55:44.000Z",
    "edit_controls": {
      "editable_until": "2026-06-14T18:55:44.000Z",
      "edits_remaining": 5,
      "is_edit_eligible": false
    },
    "edit_history_tweet_ids": [
      "2066218044133962140"
    ],
    "entities": {
      "mentions": [
        {
          "end": 18,
          "id": "2042276998668525573",
          "start": 3,
          "username": "SakurabaAya514"
        }
      ]
    },
    "geo": {},
    "id": "2066218044133962140",
    "lang": "zh",
    "note_tweet": {
      "entities": {}
    },
    "possibly_sensitive": false,
    "public_metrics": {
      "bookmark_count": 0,
      "impression_count": 0,
      "like_count": 0,
      "quote_count": 0,
      "reply_count": 0,
      "retweet_count": 1
    },
    "referenced_tweets": [
      {
        "id": "2066210545645342801",
        "type": "retweeted"
      }
    ],
    "reply_settings": "everyone",
    "text": "RT @SakurabaAya514: 冷知识：今天是个特殊的日子\n按照美国东部时间（夏令时比北京时间晚12小时），今天是特朗普的生日（6月14日）\n按照北京时间，今天是习近平的生日（6月15日）\n他们都在各自的国家推动了深刻的结构性变革，并共同主导了21世纪大国博弈的走向 h…"
  },
  "includes": {
    "media": [
      {
        "height": 324,
        "media_key": "3_2066210543246188544",
        "public_metrics": {},
        "type": "photo",
        "url": "https://pbs.twimg.com/media/HKynirVbIAAx26-.jpg",
        "width": 316
      }
    ],
    "tweets": [
      {
        "article": {},
        "attachments": {},
        "author_id": "1545801302617116672",
        "context_annotations": [
          {
            "domain": {
              "description": "Named people in the world like Nelson Mandela",
              "id": "10",
              "name": "Person"
            },
            "entity": {
              "description": "Xi Jinping",
              "id": "852769182315761664",
              "name": "Xi Jinping"
            }
          },
          {
            "domain": {
              "description": "Politicians in the world, like Joe Biden",
              "id": "35",
              "name": "Politician"
            },
            "entity": {
              "description": "Xi Jinping",
              "id": "852769182315761664",
              "name": "Xi Jinping"
            }
          },
          {
            "domain": {
              "description": "A taxonomy of user interests. ",
              "id": "131",
              "name": "Unified Twitter Taxonomy"
            },
            "entity": {
              "description": "Politics",
              "id": "847878884917886977",
              "name": "Politics"
            }
          },
          {
            "domain": {
              "description": "A taxonomy of user interests. ",
              "id": "131",
              "name": "Unified Twitter Taxonomy"
            },
            "entity": {
              "description": "Xi Jinping",
              "id": "852769182315761664",
              "name": "Xi Jinping"
            }
          },
          {
            "domain": {
              "description": "A taxonomy of user interests. ",
              "id": "131",
              "name": "Unified Twitter Taxonomy"
            },
            "entity": {
              "description": "Politician",
              "id": "1070032753834438656",
              "name": "Political figures"
            }
          }
        ],
        "conversation_id": "2066218044133962140",
        "created_at": "2026-06-14T17:55:44.000Z",
        "edit_controls": {
          "editable_until": "2026-06-14T18:55:44.000Z",
          "edits_remaining": 5,
          "is_edit_eligible": false
        },
        "edit_history_tweet_ids": [
          "2066218044133962140"
        ],
        "entities": {
          "mentions": [
            {
              "end": 18,
              "id": "2042276998668525573",
              "start": 3,
              "username": "SakurabaAya514"
            }
          ]
        },
        "geo": {},
        "id": "2066218044133962140",
        "lang": "zh",
        "note_tweet": {
          "entities": {}
        },
        "possibly_sensitive": false,
        "public_metrics": {
          "bookmark_count": 0,
          "impression_count": 0,
          "like_count": 0,
          "quote_count": 0,
          "reply_count": 0,
          "retweet_count": 1
        },
        "referenced_tweets": [
          {
            "id": "2066210545645342801",
            "type": "retweeted"
          }
        ],
        "reply_settings": "everyone",
        "text": "RT @SakurabaAya514: 冷知识：今天是个特殊的日子\n按照美国东部时间（夏令时比北京时间晚12小时），今天是特朗普的生日（6月14日）\n按照北京时间，今天是习近平的生日（6月15日）\n他们都在各自的国家推动了深刻的结构性变革，并共同主导了21世纪大国博弈的走向 h…"
      },
      {
        "article": {},
        "attachments": {
          "media_keys": [
            "3_2066210543246188544"
          ]
        },
        "author_id": "2042276998668525573",
        "context_annotations": [
          {
            "domain": {
              "description": "Named people in the world like Nelson Mandela",
              "id": "10",
              "name": "Person"
            },
            "entity": {
              "description": "Xi Jinping",
              "id": "852769182315761664",
              "name": "Xi Jinping"
            }
          },
          {
            "domain": {
              "description": "Politicians in the world, like Joe Biden",
              "id": "35",
              "name": "Politician"
            },
            "entity": {
              "description": "Xi Jinping",
              "id": "852769182315761664",
              "name": "Xi Jinping"
            }
          },
          {
            "domain": {
              "description": "A taxonomy of user interests. ",
              "id": "131",
              "name": "Unified Twitter Taxonomy"
            },
            "entity": {
              "description": "Politics",
              "id": "847878884917886977",
              "name": "Politics"
            }
          },
          {
            "domain": {
              "description": "A taxonomy of user interests. ",
              "id": "131",
              "name": "Unified Twitter Taxonomy"
            },
            "entity": {
              "description": "Xi Jinping",
              "id": "852769182315761664",
              "name": "Xi Jinping"
            }
          },
          {
            "domain": {
              "description": "A taxonomy of user interests. ",
              "id": "131",
              "name": "Unified Twitter Taxonomy"
            },
            "entity": {
              "description": "Politician",
              "id": "1070032753834438656",
              "name": "Political figures"
            }
          }
        ],
        "conversation_id": "2066210545645342801",
        "created_at": "2026-06-14T17:25:57.000Z",
        "edit_controls": {
          "editable_until": "2026-06-14T18:25:57.000Z",
          "edits_remaining": 5,
          "is_edit_eligible": true
        },
        "edit_history_tweet_ids": [
          "2066210545645342801"
        ],
        "entities": {
          "urls": [
            {
              "display_url": "pic.x.com/0ioMJlIsxz",
              "end": 141,
              "expanded_url": "https://x.com/SakurabaAya514/status/2066210545645342801/photo/1",
              "media_key": "3_2066210543246188544",
              "start": 118,
              "url": "https://t.co/0ioMJlIsxz"
            }
          ]
        },
        "geo": {},
        "id": "2066210545645342801",
        "lang": "zh",
        "note_tweet": {
          "entities": {}
        },
        "possibly_sensitive": false,
        "public_metrics": {
          "bookmark_count": 1,
          "impression_count": 132,
          "like_count": 5,
          "quote_count": 0,
          "reply_count": 3,
          "retweet_count": 1
        },
        "reply_settings": "everyone",
        "text": "冷知识：今天是个特殊的日子\n按照美国东部时间（夏令时比北京时间晚12小时），今天是特朗普的生日（6月14日）\n按照北京时间，今天是习近平的生日（6月15日）\n他们都在各自的国家推动了深刻的结构性变革，并共同主导了21世纪大国博弈的走向 https://t.co/0ioMJlIsxz"
      }
    ],
    "users": [
      {
        "created_at": "2022-07-09T16:05:40.000Z",
        "description": "MTF🏳️‍⚧️ 无证含糖 怀疑状态\n戒 OD & 自伤 中......\n要和窝互 fo 嘛 qwq（？\n@xunfengjun666 转生😈👍\n求求你了求求你了进来玩⬇️",
        "entities": {
          "description": {
            "mentions": [
              {
                "end": 67,
                "start": 53,
                "username": "xunfengjun666"
              }
            ]
          },
          "url": {
            "urls": [
              {
                "display_url": "minecraftxfj.top",
                "end": 23,
                "expanded_url": "https://minecraftxfj.top",
                "start": 0,
                "url": "https://t.co/zYxENR54VJ"
              }
            ]
          }
        },
        "id": "1545801302617116672",
        "location": "Inner Mongolia,P.R.China",
        "name": "夜桜侵峰～",
        "pinned_tweet_id": "2061128300869919213",
        "profile_image_url": "https://pbs.twimg.com/profile_images/1995204955968557056/XnPwmQB3_normal.jpg",
        "protected": false,
        "public_metrics": {
          "followers_count": 38,
          "following_count": 106,
          "like_count": 48,
          "listed_count": 0,
          "media_count": 90,
          "tweet_count": 748
        },
        "url": "https://t.co/zYxENR54VJ",
        "username": "Minecraftxfj",
        "verified": false
      },
      {
        "created_at": "2026-04-09T16:22:54.000Z",
        "description": "来自坎通国（现居巴蜀）/东方project/魔裁/Arcaea/舞萌/键政⚠️/双相情感障碍⚠️/亚文化B/欢迎互fo（会看成分致歉）/LGBTQ+🏳️‍🌈友好/友跨🏳️‍⚧️\n主要在X上网冲浪评论搞抽象为主，发帖主要是日常生活和碎碎念，以及负面推文⚠️",
        "id": "2042276998668525573",
        "location": "真理就是没真理！",
        "name": "赤月",
        "pinned_tweet_id": "2063643511128522806",
        "profile_image_url": "https://pbs.twimg.com/profile_images/2062600655634907136/sl1r5PSg_normal.jpg",
        "protected": false,
        "public_metrics": {
          "followers_count": 651,
          "following_count": 778,
          "like_count": 8825,
          "listed_count": 0,
          "media_count": 337,
          "tweet_count": 2747
        },
        "username": "SakurabaAya514",
        "verified": false
      }
    ]
  }
}