{
  "data": {
    "article": {},
    "attachments": {},
    "author_id": "1545801302617116672",
    "conversation_id": "2075610713062867196",
    "created_at": "2026-07-10T18:05:14.000Z",
    "edit_controls": {
      "editable_until": "2026-07-10T19:05:14.000Z",
      "edits_remaining": 5,
      "is_edit_eligible": false
    },
    "edit_history_tweet_ids": [
      "2075642517215981599"
    ],
    "entities": {
      "mentions": [
        {
          "end": 14,
          "id": "2049103771796660224",
          "start": 0,
          "username": "theIrisWithin"
        }
      ]
    },
    "geo": {},
    "id": "2075642517215981599",
    "in_reply_to_user_id": "2049103771796660224",
    "lang": "qme",
    "note_tweet": {
      "entities": {}
    },
    "possibly_sensitive": false,
    "public_metrics": {
      "bookmark_count": 0,
      "impression_count": 0,
      "like_count": 0,
      "quote_count": 0,
      "reply_count": 0,
      "retweet_count": 0
    },
    "referenced_tweets": [
      {
        "id": "2075610713062867196",
        "type": "replied_to"
      }
    ],
    "reply_settings": "everyone",
    "text": "@theIrisWithin 🤔🤔🤔"
  },
  "includes": {
    "tweets": [
      {
        "article": {},
        "attachments": {},
        "author_id": "1545801302617116672",
        "conversation_id": "2075610713062867196",
        "created_at": "2026-07-10T18:05:14.000Z",
        "edit_controls": {
          "editable_until": "2026-07-10T19:05:14.000Z",
          "edits_remaining": 5,
          "is_edit_eligible": false
        },
        "edit_history_tweet_ids": [
          "2075642517215981599"
        ],
        "entities": {
          "mentions": [
            {
              "end": 14,
              "id": "2049103771796660224",
              "start": 0,
              "username": "theIrisWithin"
            }
          ]
        },
        "geo": {},
        "id": "2075642517215981599",
        "in_reply_to_user_id": "2049103771796660224",
        "lang": "qme",
        "note_tweet": {
          "entities": {}
        },
        "possibly_sensitive": false,
        "public_metrics": {
          "bookmark_count": 0,
          "impression_count": 0,
          "like_count": 0,
          "quote_count": 0,
          "reply_count": 0,
          "retweet_count": 0
        },
        "referenced_tweets": [
          {
            "id": "2075610713062867196",
            "type": "replied_to"
          }
        ],
        "reply_settings": "everyone",
        "text": "@theIrisWithin 🤔🤔🤔"
      },
      {
        "article": {},
        "attachments": {},
        "author_id": "2049103771796660224",
        "conversation_id": "2075610713062867196",
        "created_at": "2026-07-10T15:58:51.000Z",
        "edit_controls": {
          "editable_until": "2026-07-10T16:58:51.000Z",
          "edits_remaining": 5,
          "is_edit_eligible": true
        },
        "edit_history_tweet_ids": [
          "2075610713062867196"
        ],
        "entities": {
          "urls": [
            {
              "description": "P’s Space · 0 listening · Where live audio conversations happen",
              "display_url": "x.com/i/spaces/1dKrP…",
              "end": 23,
              "expanded_url": "https://x.com/i/spaces/1dKrPPqbaZYJX",
              "images": [
                {
                  "height": 630,
                  "url": "https://pbs.twimg.com/news_img/2075610714438565888/0mhmKBsh?format=jpg&name=orig",
                  "width": 1200
                },
                {
                  "height": 150,
                  "url": "https://pbs.twimg.com/news_img/2075610714438565888/0mhmKBsh?format=jpg&name=150x150",
                  "width": 150
                }
              ],
              "start": 0,
              "status": 200,
              "title": "Happening now: 😂",
              "unwound_url": "https://twitter.com/i/spaces/1dKrPPqbaZYJX/peek",
              "url": "https://t.co/jPdAIuIyf2"
            }
          ]
        },
        "geo": {},
        "id": "2075610713062867196",
        "lang": "zxx",
        "note_tweet": {
          "entities": {}
        },
        "possibly_sensitive": false,
        "public_metrics": {
          "bookmark_count": 0,
          "impression_count": 112,
          "like_count": 0,
          "quote_count": 0,
          "reply_count": 7,
          "retweet_count": 0
        },
        "reply_settings": "everyone",
        "text": "https://t.co/jPdAIuIyf2"
      }
    ],
    "users": [
      {
        "created_at": "2022-07-09T16:05:40.000Z",
        "description": "✨星海幽暗，孤寂无垠，直到有人点燃了自我，宇宙才拥有最初的光✨\nMtF🏳️‍⚧️🍥｜嵌入式｜编程｜DIY｜数码科技｜二次元\n❤️要和窝互 fo 嘛 qwq🥹（？\nUTC+8🤨简中/Eng🤯怀疑状态☹️高三😱戒 OD & 自伤 ing......😇\n@xunfengjun666 转生？！😨",
        "entities": {
          "description": {
            "mentions": [
              {
                "end": 138,
                "start": 124,
                "username": "xunfengjun666"
              }
            ]
          },
          "url": {
            "urls": [
              {
                "display_url": "minecraftxfj.top",
                "end": 23,
                "expanded_url": "https://minecraftxfj.top",
                "start": 0,
                "url": "https://t.co/zYxENR54VJ"
              }
            ]
          }
        },
        "id": "1545801302617116672",
        "location": "Inner Mongolia,P.R.China",
        "name": "夜桜侵雪～🫪",
        "profile_image_url": "https://pbs.twimg.com/profile_images/1995204955968557056/XnPwmQB3_normal.jpg",
        "protected": false,
        "public_metrics": {
          "followers_count": 408,
          "following_count": 468,
          "like_count": 128,
          "listed_count": 0,
          "media_count": 264,
          "tweet_count": 2288
        },
        "url": "https://t.co/zYxENR54VJ",
        "username": "Minecraftxfj",
        "verified": true
      },
      {
        "created_at": "2026-04-28T12:31:01.000Z",
        "description": "Y the fvk am i still here breathing？",
        "id": "2049103771796660224",
        "location": "dream",
        "name": "P",
        "profile_image_url": "https://pbs.twimg.com/profile_images/2074003869944975360/3LrYAOVh_normal.jpg",
        "protected": false,
        "public_metrics": {
          "followers_count": 105,
          "following_count": 123,
          "like_count": 3824,
          "listed_count": 1,
          "media_count": 118,
          "tweet_count": 763
        },
        "url": "",
        "username": "theIrisWithin",
        "verified": false
      }
    ]
  }
}